ag_contrib/http_client.py
ag_contrib/utils.py
autograder_contrib-1.0.0.dist-info/LICENSE
autograder_contrib-1.0.0.dist-info/METADATA
autograder_contrib-1.0.0.dist-info/WHEEL
autograder_contrib-1.0.0.dist-info/entry_points.txt
autograder_contrib-1.0.0.dist-info/top_level.txt
autograder_contrib-1.0.0.dist-info/RECORD
