Metadata-Version: 2.1
Name: autograder-contrib
Version: 1.0.0
Summary: A command-line http client and other utilities for writing applications that use the autograder.io API.
Home-page: https://github.com/eecs-autograder/autograder-contrib
Author: James Perretta
Author-email: jameslp@umich.edu
License: GNU Lesser General Public License v3
Keywords: autograder
Platform: UNKNOWN
Classifier: Programming Language :: Python :: 3.6
Requires-Dist: requests
